toran/__init__.py
toran/maths/__init__.py
toran/maths/formulae.py
toran_pylib-0.0.3.dist-info/LICENSE
toran_pylib-0.0.3.dist-info/METADATA
toran_pylib-0.0.3.dist-info/WHEEL
toran_pylib-0.0.3.dist-info/top_level.txt
toran_pylib-0.0.3.dist-info/RECORD
